dftd4-4.0.0.dist-info/RECORD
dftd4-4.0.0.dist-info/WHEEL
dftd4-4.0.0.dist-info/METADATA
dftd4/test_library.py
dftd4/references.json
dftd4/ase.py
dftd4/library.py
dftd4/test_ase.py
dftd4/interface.py
dftd4/__init__.py
dftd4/test_parameters.py
dftd4/pyscf.py
dftd4/test_qcschema.py
dftd4/_libdftd4.cpython-310-darwin.so
dftd4/parameters.toml
dftd4/parameters.py
dftd4/qcschema.py
dftd4/test_interface.py
dftd4/data.py
dftd4/test_pyscf.py
dftd4/.dylibs/libgfortran.5.dylib
dftd4/.dylibs/libquadmath.0.dylib
dftd4/.dylibs/libgcc_s.1.1.dylib
dftd4/.dylibs/libgomp.1.dylib
